missim_cli/__init__.py
missim_cli/banner.py
missim_cli/cli.py
missim_cli/helpers.py
missim_cli/render_fbx.py
missim_cli/docker/docker-compose.dev.yaml
missim_cli/docker/docker-compose.network-host.yaml
missim_cli/docker/docker-compose.network-shared.yaml
missim_cli/docker/docker-compose.prod.yaml
missim_cli/docker/docker-compose.ue_editor.host.yaml
missim_cli/docker/docker-compose.ue_editor.shared.yaml
missim_cli/docker/docker-compose.ue_editor.yaml
missim_cli/docker/docker-compose.ue_editor_nas_cache.yaml
missim_cli/docker/docker-compose.ue_pixel_streaming.yaml
missim_cli/docker/docker-compose.ue_standalone.host.yaml
missim_cli/docker/docker-compose.ue_standalone.shared.yaml
missim_cli/docker/docker-compose.ue_standalone.yaml
missim_cli/docker/docker-compose.yaml
missim_cli/groups/__init__.py
missim_cli/groups/base.py
missim_cli/groups/git.py
missim_cli/groups/image.py
missim_cli/groups/setup.py
missim_cli-2.0.0.dist-info/METADATA
missim_cli-2.0.0.dist-info/WHEEL
missim_cli-2.0.0.dist-info/entry_points.txt
missim_cli-2.0.0.dist-info/top_level.txt
missim_cli-2.0.0.dist-info/zip-safe
missim_cli-2.0.0.dist-info/RECORD
